scrapy_ipfs_filecoin/__init__.py
scrapy_ipfs_filecoin/client.py
scrapy_ipfs_filecoin/feedexport.py
scrapy_ipfs_filecoin/pipelines.py
scrapy_ipfs_filecoin-0.0.3.dist-info/LICENSE.txt
scrapy_ipfs_filecoin-0.0.3.dist-info/METADATA
scrapy_ipfs_filecoin-0.0.3.dist-info/WHEEL
scrapy_ipfs_filecoin-0.0.3.dist-info/top_level.txt
scrapy_ipfs_filecoin-0.0.3.dist-info/RECORD
