Metadata-Version: 2.1
Name: scrapy-ipfs-filecoin
Version: 0.0.3
Summary: Scrapy is a popular open-source and collaborative python framework for extracting the data you need from websites. scrapy-ipfs-filecoin provides scrapy pipelines and feed exports to store items into IPFS and Filecoin using services like Web3.Storage, LightHouse.Storage, Estuary, Pinata, Moralis, Filebase or any s3 compatible services.
Home-page: https://github.com/pawanpaudel93/scrapy-ipfs-filecoin
Author: Pawan Paudel
Author-email: pawanpaudel93@gmail.com
License: ISC
Classifier: License :: OSI Approved :: MIT License
Classifier: Development Status :: 3 - Alpha
Classifier: Programming Language :: Python :: 3
Classifier: Programming Language :: Python :: 3.6
Classifier: Programming Language :: Python :: 3.7
Classifier: Programming Language :: Python :: 3.8
Classifier: Operating System :: OS Independent
Requires-Python: >=3.0
License-File: LICENSE.txt
Requires-Dist: requests
